collect_logs/__init__.py
collect_logs/main.yml
collect_logs/plugin.spec
collect_logs/tasks/collect_host_logs.yml
collect_logs/tasks/collect_sosreport.yml
collect_logs/vars/default_archives_list.yml
infrared_collect_logs-3.0.0.dist-info/DESCRIPTION.rst
infrared_collect_logs-3.0.0.dist-info/METADATA
infrared_collect_logs-3.0.0.dist-info/RECORD
infrared_collect_logs-3.0.0.dist-info/WHEEL
infrared_collect_logs-3.0.0.dist-info/entry_points.txt
infrared_collect_logs-3.0.0.dist-info/metadata.json
infrared_collect_logs-3.0.0.dist-info/pbr.json
infrared_collect_logs-3.0.0.dist-info/top_level.txt
